topsis/__init__.py
topsis/topsis.py
topsis_Bhavya_Jaiswal_102203087-1.0.3.dist-info/METADATA
topsis_Bhavya_Jaiswal_102203087-1.0.3.dist-info/WHEEL
topsis_Bhavya_Jaiswal_102203087-1.0.3.dist-info/entry_points.txt
topsis_Bhavya_Jaiswal_102203087-1.0.3.dist-info/top_level.txt
topsis_Bhavya_Jaiswal_102203087-1.0.3.dist-info/RECORD
