Metadata-Version: 2.2
Name: topsis_Bhavya_Jaiswal_102203087
Version: 1.0.3
Summary: A Python package to perform TOPSIS (Technique for Order Preference by Similarity to Ideal Solution)
Home-page: https://github.com/bhavyajaiswal27/topsis_BhavyaJaiswal_102203087
Author: Bhavya Jaiswal
Author-email: bhavya.jaiswal27@gmail.com
Classifier: Programming Language :: Python :: 3
Classifier: License :: OSI Approved :: MIT License
Classifier: Operating System :: OS Independent
Requires-Python: >=3.6
Requires-Dist: numpy
Requires-Dist: pandas
Dynamic: author
Dynamic: author-email
Dynamic: classifier
Dynamic: description
Dynamic: description-content-type
Dynamic: home-page
Dynamic: requires-dist
Dynamic: requires-python
Dynamic: summary
